<annotation>
	<folder>img_g</folder>
	<filename>IMG20231205184038_noisy_blurred_2_z1.jpg</filename>
	<path>F:\zl\img_g\IMG20231205184038_noisy_blurred_2.jpg</path>
	<source>
		<database>Unknown</database>
	</source>
	<size>
		<width>300</width>
		<height>666</height>
		<depth>3</depth>
	</size>
	<segmented>0</segmented>
	<object>
		<name>white mark</name>
		<pose>Unspecified</pose>
		<truncated>0</truncated>
		<difficult>0</difficult>
		<bndbox>
			<xmin>91</xmin>
			<ymin>396</ymin>
			<xmax>111</xmax>
			<ymax>425</ymax>
		</bndbox>
	</object>
	<object>
		<name>off-centered</name>
		<pose>Unspecified</pose>
		<truncated>0</truncated>
		<difficult>0</difficult>
		<bndbox>
			<xmin>50</xmin>
			<ymin>281</ymin>
			<xmax>109</xmax>
			<ymax>341</ymax>
		</bndbox>
	</object>
</annotation>