<annotation>
	<folder>img_g</folder>
	<filename>IMG20231205185402_noisy_blurred_2_z1.jpg</filename>
	<path>F:\zl\img_g\IMG20231205185402_noisy_blurred_2.jpg</path>
	<source>
		<database>Unknown</database>
	</source>
	<size>
		<width>300</width>
		<height>666</height>
		<depth>3</depth>
	</size>
	<segmented>0</segmented>
	<object>
		<name>white mark</name>
		<pose>Unspecified</pose>
		<truncated>0</truncated>
		<difficult>0</difficult>
		<bndbox>
			<xmin>123</xmin>
			<ymin>449</ymin>
			<xmax>142</xmax>
			<ymax>465</ymax>
		</bndbox>
	</object>
	<object>
		<name>joint line</name>
		<pose>Unspecified</pose>
		<truncated>0</truncated>
		<difficult>0</difficult>
		<bndbox>
			<xmin>132</xmin>
			<ymin>425</ymin>
			<xmax>141</xmax>
			<ymax>445</ymax>
		</bndbox>
	</object>
</annotation>